CONTRIBUTORS
LICENSE
README.rst
VERSION
requirements.txt
yaq/__init__.py
yaq-0.0.0.dist-info/DESCRIPTION.rst
yaq-0.0.0.dist-info/METADATA
yaq-0.0.0.dist-info/RECORD
yaq-0.0.0.dist-info/WHEEL
yaq-0.0.0.dist-info/metadata.json
yaq-0.0.0.dist-info/top_level.txt
