Metadata-Version: 2.0
Name: yaq
Version: 0.0.0
Summary: Yet another acquisition.
Home-page: https://github.com/wright-group/yaq
Author: Blaise Thompson
Author-email: blaise@untzag.com
License: MIT
Keywords: spectroscopy science multidimensional
Platform: UNKNOWN
Classifier: Development Status :: 1 - Planning
Classifier: Intended Audience :: Science/Research
Classifier: License :: OSI Approved :: MIT License
Classifier: Natural Language :: English
Classifier: Programming Language :: Python :: 3
Classifier: Programming Language :: Python :: 3.3
Classifier: Programming Language :: Python :: 3.4
Classifier: Programming Language :: Python :: 3.5
Classifier: Topic :: Scientific/Engineering
Requires-Dist: wrighttools
